GSSR/GSSR.py
GSSR/__init__.py
GSSR/__main__.py
GSSR/analysis/__init__.py
GSSR/analysis/aggregation.py
GSSR/analysis/analysis.py
GSSR/analysis/grapher.py
GSSR/analysis/preprocessing.py
GSSR/analysis/report.py
GSSR/csv/DCGM_Def_Metrics.csv
GSSR/export/export.py
GSSR/fonts/DejaVuSans-Bold.ttf
GSSR/fonts/DejaVuSans-Oblique.ttf
GSSR/fonts/DejaVuSans.ttf
GSSR/io/__init__.py
GSSR/io/base_io.py
GSSR/io/binary_io.py
GSSR/io/format.py
GSSR/io/json_io.py
GSSR/io/sql_io.py
GSSR/profile/__init__.py
GSSR/profile/gpu_metrics_profiler.py
GSSR/profile/metrics.py
GSSR/utils/__init__.py
GSSR/utils/import_check.py
GSSR/utils/slurm_handler.py
gssr-0.4.0.dist-info/licenses/AUTHORS.md
gssr-0.4.0.dist-info/licenses/LICENSE
gssr-0.4.0.dist-info/METADATA
gssr-0.4.0.dist-info/WHEEL
gssr-0.4.0.dist-info/entry_points.txt
gssr-0.4.0.dist-info/top_level.txt
gssr-0.4.0.dist-info/RECORD
