Metadata-Version: 2.4
Name: gssr
Version: 0.4.0
License-Expression: BSD-3-Clause
Project-URL: Repository, https://github.com/eth-cscs/GPU-saturation-scorer.git
Requires-Python: >=3.9
License-File: LICENSE
License-File: AUTHORS.md
Requires-Dist: pandas
Requires-Dist: matplotlib
Requires-Dist: seaborn
Requires-Dist: scipy
Requires-Dist: numpy
Requires-Dist: tabulate
Requires-Dist: rich
Requires-Dist: fpdf2
Requires-Dist: tqdm
Dynamic: license-file
